format_conversation_dataset/__init__.py
format_conversation_dataset/_modidx.py
format_conversation_dataset/format_transcription.py
format_conversation_dataset-0.0.1.dist-info/LICENSE
format_conversation_dataset-0.0.1.dist-info/METADATA
format_conversation_dataset-0.0.1.dist-info/WHEEL
format_conversation_dataset-0.0.1.dist-info/entry_points.txt
format_conversation_dataset-0.0.1.dist-info/top_level.txt
format_conversation_dataset-0.0.1.dist-info/RECORD
